seminal_root_angle
