Metadata-Version: 2.1
Name: seminal-root-angle
Version: 0.0.6
Summary: Extract seminal root angle from rhizobox images
Home-page: https://github.com/Abe404/seminal_root_angle
Author: Abraham George Smith
Author-email: abe@abesmith.co.uk
License: GPLv3
Download-URL: https://github.com/Abe404/seminal_root_angle/archive/refs/tags/0.0.6.tar.gz
Keywords: ROOT,ANGLE,PHENOTYPING
Platform: UNKNOWN
Classifier: Intended Audience :: Developers
Classifier: Programming Language :: Python :: 3
Classifier: License :: OSI Approved :: GNU General Public License v3 (GPLv3)
Classifier: Operating System :: OS Independent
